tomotwin/__init__.py
tomotwin/bibtex.py
tomotwin/constants.py
tomotwin/convert.py
tomotwin/protocols.conf
tomotwin/tomotwin_logo.png
tomotwin/wizards.py
tomotwin/protocols/__init__.py
tomotwin/protocols/protocol_base.py
tomotwin/protocols/protocol_create_masks.py
tomotwin/protocols/protocol_picking_cluster.py
tomotwin/protocols/protocol_picking_cluster_umap.py
tomotwin/protocols/protocol_picking_ref.py
tomotwin/tests/__init__.py
tomotwin/tests/test_protocols_tomotwin.py
tomotwin/viewers/__init__.py
tomotwin/viewers/viewers_data.py
tomotwin/viewers/views_tkinter_tree.py
scipion_em_tomotwin-3.5.3.dist-info/LICENSE
scipion_em_tomotwin-3.5.3.dist-info/METADATA
scipion_em_tomotwin-3.5.3.dist-info/WHEEL
scipion_em_tomotwin-3.5.3.dist-info/entry_points.txt
scipion_em_tomotwin-3.5.3.dist-info/top_level.txt
scipion_em_tomotwin-3.5.3.dist-info/RECORD
